MANIFEST.in
mrp_jit.xml
setup.py
./__init__.py
./__openerp__.py
i18n/ar.po
i18n/bg.po
i18n/bs.po
i18n/ca.po
i18n/cs.po
i18n/da.po
i18n/de.po
i18n/el.po
i18n/en_GB.po
i18n/es.po
i18n/es_AR.po
i18n/es_CR.po
i18n/es_EC.po
i18n/es_MX.po
i18n/es_VE.po
i18n/et.po
i18n/fi.po
i18n/fr.po
i18n/gl.po
i18n/hr.po
i18n/hu.po
i18n/id.po
i18n/it.po
i18n/ja.po
i18n/kab.po
i18n/ko.po
i18n/ko_KO.po
i18n/lt.po
i18n/mk.po
i18n/ml.po
i18n/mn.po
i18n/mrp_jit.pot
i18n/nb.po
i18n/nl.po
i18n/nl_BE.po
i18n/oc.po
i18n/pl.po
i18n/pt.po
i18n/pt_BR.po
i18n/ro.po
i18n/ru.po
i18n/sk.po
i18n/sl.po
i18n/sq.po
i18n/sr.po
i18n/sr@latin.po
i18n/sv.po
i18n/ta.po
i18n/tr.po
i18n/uk.po
i18n/vi.po
i18n/zh_CN.po
i18n/zh_TW.po
openerp_mrp_jit.egg-info/PKG-INFO
openerp_mrp_jit.egg-info/SOURCES.txt
openerp_mrp_jit.egg-info/dependency_links.txt
openerp_mrp_jit.egg-info/requires.txt
openerp_mrp_jit.egg-info/top_level.txt
test/mrp_jit.yml